aiohttp_limit/__init__.py
aiohttp_sentry/__init__.py
aiohttp_limit-0.1.0.dist-info/LICENSE
aiohttp_limit-0.1.0.dist-info/METADATA
aiohttp_limit-0.1.0.dist-info/WHEEL
aiohttp_limit-0.1.0.dist-info/top_level.txt
aiohttp_limit-0.1.0.dist-info/RECORD
