Metadata-Version: 2.1
Name: aiohttp-limit
Version: 0.1.0
Summary: An aiohttp middleware for limiting connections
Home-page: https://github.com/underyx/aiohttp-limit
Author: Bence Nagy
Author-email: bence@underyx.me
Maintainer: Bence Nagy
Maintainer-email: bence@underyx.me
License: UNKNOWN
Download-URL: https://github.com/underyx/aiohttp-limit/releases
Platform: UNKNOWN
Classifier: Development Status :: 3 - Alpha
Classifier: License :: OSI Approved :: MIT License
Classifier: Operating System :: OS Independent
Classifier: Programming Language :: Python :: 3 :: Only
Classifier: Programming Language :: Python :: 3.7
Requires-Dist: aiohttp (>=2.3)
